pyception/__init__.py
pyception/application.py
pyception/collection.py
pyception/configuration.py
pyception/data.py
pyception/io.py
pyception/networking.py
pyception/security.py
pyception/system.py
pyception/text.py
pyception/wrapper.py
pyception-0.1.4.dist-info/DESCRIPTION.rst
pyception-0.1.4.dist-info/METADATA
pyception-0.1.4.dist-info/metadata.json
pyception-0.1.4.dist-info/RECORD
pyception-0.1.4.dist-info/top_level.txt
pyception-0.1.4.dist-info/WHEEL
